fuzzysearch.py
simple_fuzzysearch-0.0.5.dist-info/DESCRIPTION.rst
simple_fuzzysearch-0.0.5.dist-info/metadata.json
simple_fuzzysearch-0.0.5.dist-info/METADATA
simple_fuzzysearch-0.0.5.dist-info/RECORD
simple_fuzzysearch-0.0.5.dist-info/WHEEL
simple_fuzzysearch-0.0.5.dist-info/top_level.txt
