Metadata-Version: 2.0
Name: simple-fuzzysearch
Version: 0.0.5
Summary: Matching a string with partial input
Home-page: https://github.com/ferhatelmas/simple-fuzzysearch
Author: Ferhat Elmas
Author-email: elmas.ferhat@gmail.com
License: MIT
Platform: UNKNOWN
Classifier: Programming Language :: Python :: 2
Classifier: Programming Language :: Python :: 3
Classifier: Intended Audience :: Developers
Classifier: License :: OSI Approved :: MIT License
Classifier: Topic :: Software Development :: Libraries
Classifier: Topic :: Utilities
